extras/__init__.py
extras/divide.py
extras/multiply.py
publication_packages-0.0.1.dist-info/METADATA
publication_packages-0.0.1.dist-info/WHEEL
publication_packages-0.0.1.dist-info/top_level.txt
publication_packages-0.0.1.dist-info/RECORD
